gda_score_code_test-2.5.13.dist-info/METADATA
gda_score_code_test-2.5.13.dist-info/RECORD
gda_score_code_test-2.5.13.dist-info/WHEEL
gda_score_code_test-2.5.13.dist-info/entry_points.txt
gda_score_code_test-2.5.13.dist-info/top_level.txt
gdascore/__init__.py
gdascore/cli.py
gdascore/dupCheck.py
gdascore/gdaAttack.py
gdascore/gdaQuery.py
gdascore/gdaScore.py
gdascore/gdaTools.py
gdascore/sampleConfig.py
gdascore/global_config/__init__.py
gdascore/global_config/master.json
