Metadata-Version: 2.1
Name: gda-score-code-test
Version: 2.5.13
Summary: Tools for generating General Data Anonymity Scores (www.gda-score.org)
Home-page: https://github.com/gda-score/code
Author: Paul Francis
License: UNKNOWN
Platform: UNKNOWN
Classifier: Programming Language :: Python :: 3.7
Classifier: License :: OSI Approved :: MIT License
Classifier: Operating System :: OS Independent
Requires-Dist: coloredlogs (>=14.0)
Requires-Dist: matplotlib (>=3.0.2)
Requires-Dist: numpy (>=1.16.0)
Requires-Dist: pandas (>=1.1.0)
Requires-Dist: psycopg2 (>=2.8.3)
Requires-Dist: python-dateutil (>=2.7.5)
Requires-Dist: simplejson (>=3.16.0)
